README.md
setup.py
pizza_shop.egg-info/PKG-INFO
pizza_shop.egg-info/SOURCES.txt
pizza_shop.egg-info/dependency_links.txt
pizza_shop.egg-info/entry_points.txt
pizza_shop.egg-info/top_level.txt
pizzashop/__init__.py
pizzashop/config.py
pizzashop/game.py
pizzashop/main.py
pizzashop/stories.py
pizzashop/stories/pizza.txt
pizzashop/stories/story_1.txt
pizzashop/stories/story_10.txt
pizzashop/stories/story_11.txt
pizzashop/stories/story_2.txt
pizzashop/stories/story_3.txt
pizzashop/stories/story_4.txt
pizzashop/stories/story_5.txt
pizzashop/stories/story_6.txt
pizzashop/stories/story_7.txt
pizzashop/stories/story_8.txt
pizzashop/stories/story_9.txt