Metadata-Version: 1.0
Name: pizza-shop
Version: 0.1.2
Summary: UNKNOWN
Home-page: UNKNOWN
Author: jacksonelfers
Author-email: JacksonElfers@hotmail.com
License: Creative Commons Attribution-Noncommercial-Share Alike license
Platform: UNKNOWN
